reuterspy/__init__.py
reuterspy/utils/__init__.py
reuterspy/utils/api.py
reuterspy/utils/format_data.py
reuterspy-1.0.dist-info/LICENSE
reuterspy-1.0.dist-info/METADATA
reuterspy-1.0.dist-info/WHEEL
reuterspy-1.0.dist-info/top_level.txt
reuterspy-1.0.dist-info/RECORD
